helpsk/__init__.py
helpsk/color.py
helpsk/conversions.py
helpsk/database.py
helpsk/database_base.py
helpsk/date.py
helpsk/diff.py
helpsk/exceptions.py
helpsk/logging.py
helpsk/pandas.py
helpsk/pandas_style.py
helpsk/plot.py
helpsk/sklearn_eval.py
helpsk/sklearn_pipeline.py
helpsk/string.py
helpsk/text.py
helpsk/utility.py
helpsk/validation.py
helpsk-0.1.63.dist-info/METADATA
helpsk-0.1.63.dist-info/WHEEL
helpsk-0.1.63.dist-info/licenses/LICENSE
helpsk-0.1.63.dist-info/RECORD
