Metadata-Version: 2.4
Name: helpsk
Version: 0.1.63
Summary: Python helper functions and classes.
License-File: LICENSE
Requires-Python: >=3.11
Requires-Dist: jinja2>=3.1.5
Requires-Dist: matplotlib>=3.10.1
Requires-Dist: numpy>=2.2.3
Requires-Dist: pandas>=2.2.3
Requires-Dist: plotly-express>=0.4.1
Requires-Dist: plotly>=6.0.0
Requires-Dist: python-dateutil>=2.9.0.post0
Requires-Dist: pyyaml>=6.0.2
Requires-Dist: scikit-learn>=1.6.1
Requires-Dist: seaborn>=0.13.2
